kbostadium-0.3.0.dist-info/METADATA
kbostadium-0.3.0.dist-info/WHEEL
kbostadium-0.3.0.dist-info/entry_points.txt
kbostadium-0.3.0.dist-info/licenses/LICENSE
kbostadium/__init__.py
kbostadium/info_sta.py
kbostadium/test.ipynb
kbostadium-0.3.0.dist-info/RECORD
