Metadata-Version: 2.1
Name: kbostadium
Version: 0.3.0
Summary: Default template for PDM package
Author-Email: "<jiwon1118>" <<b23386585@gmail.com>>
License: MIT
Requires-Python: >=3.10
Requires-Dist: typer>=0.15.1
Requires-Dist: pytest>=8.3.4
Requires-Dist: jupyterlab>=4.3.5
Requires-Dist: pandas>=2.2.3
Requires-Dist: requests>=2.32.3
